crawler_utils/__init__.py
crawler_utils/_headers.py
crawler_utils/code.py
crawler_utils/cookie_pool.py
crawler_utils/mongo_cache.py
crawler_utils/redis_cache.py
crawler_utils/utils.py
flask_utils/__init__.py
flask_utils/fake.py
flask_utils/flask_env.py
flask_utils/model.py
flask_utils/restframework.py
flask_utils/views.py
icecola-0.6.dist-info/METADATA
icecola-0.6.dist-info/RECORD
icecola-0.6.dist-info/WHEEL
icecola-0.6.dist-info/top_level.txt
tests/__init__.py
tests/conftest.py
tests/test_mongo_cache.py
tests/test_utils.py
