Metadata-Version: 2.1
Name: icecola
Version: 0.6
Summary: A  util package for python
Home-page: https://github.com/Colaplusice/icecola
Author: Colaplusice
Author-email: fjl2401@163.com
License: UNKNOWN
Platform: UNKNOWN
Classifier: Programming Language :: Python :: 3
Classifier: License :: OSI Approved :: MIT License
Classifier: Operating System :: OS Independent
Requires-Python: >=3.5
Requires-Dist: pymongo (>=3.7)
Requires-Dist: pendulum (>=2.0)
Requires-Dist: peewee (>=3.9)
Requires-Dist: Flask (>=1.0)
Requires-Dist: Faker (>=1.0)
Requires-Dist: pytest (>=4.3)
